beersmith_direct/__init__.py
beersmith_direct/connector.py
beersmith_direct/i_beersmith.py
beersmith_direct/recipes.py
beersmith_direct-1.3.0.dist-info/LICENSE
beersmith_direct-1.3.0.dist-info/WHEEL
beersmith_direct-1.3.0.dist-info/METADATA
beersmith_direct-1.3.0.dist-info/RECORD
