Metadata-Version: 2.1
Name: beersmith-direct
Version: 1.3.0
Summary: Custom interface to Beersmith database
Home-page: https://github.com/lakeannebrewhouse/beersmith-direct
License: MIT
Keywords: python,mongodb,beersmith
Author: Jason Romano
Author-email: aracnid@gmail.com
Requires-Python: >=3.10,<4.0
Classifier: License :: OSI Approved :: MIT License
Classifier: Programming Language :: Python :: 3
Classifier: Programming Language :: Python :: 3.10
Classifier: Programming Language :: Python :: 3.11
Requires-Dist: aracnid-config (>=1.0,<2.0)
Requires-Dist: aracnid-logger (>=1.0,<2.0)
Requires-Dist: aracnid-utils (>=1.0,<2.0)
Requires-Dist: beautifulsoup4 (>=4.0,<5.0)
Requires-Dist: hjson (>=3.0,<4.0)
Requires-Dist: i-mongodb (>=2.0,<3.0)
Requires-Dist: xmltodict (>=0.12,<0.13)
Project-URL: Repository, https://github.com/lakeannebrewhouse/beersmith-direct
